mkdocs_slides/__init__.py
mkdocs_slides/plugin.py
mkdocs_slides/renderer.py
mkdocs_slides/slide_parser.py
mkdocs_slides/static/css/slides.css
mkdocs_slides/static/js/slides.js
mkdocs_slides/templates/slide_template.html
mkdocs_slides-0.1.3.dist-info/LICENSE
mkdocs_slides-0.1.3.dist-info/METADATA
mkdocs_slides-0.1.3.dist-info/WHEEL
mkdocs_slides-0.1.3.dist-info/entry_points.txt
mkdocs_slides-0.1.3.dist-info/RECORD
