Metadata-Version: 2.1
Name: mkdocs-slides
Version: 0.1.3
Summary: A MkDocs plugin for creating slide presentations within documentation
License: MIT
Author: Ian Derrington
Author-email: Ian.Derrington@gmail.com
Requires-Python: >=3.7,<4.0
Classifier: License :: OSI Approved :: MIT License
Classifier: Programming Language :: Python :: 3
Classifier: Programming Language :: Python :: 3.7
Classifier: Programming Language :: Python :: 3.8
Classifier: Programming Language :: Python :: 3.9
Classifier: Programming Language :: Python :: 3.10
Classifier: Programming Language :: Python :: 3.11
Classifier: Programming Language :: Python :: 3.12
Requires-Dist: PyYAML (>=6.0)
Requires-Dist: click (>=8.0)
Requires-Dist: mkdocs (>=1.4.0)
Requires-Dist: mkdocs-material (>=9.0.0)
